make_better/__init__.py
make_better/configs/pyproject.toml
make_better/configs/setup.cfg
make_better/main.py
make_better/py.typed
make_better-0.5.0.dist-info/LICENSE
make_better-0.5.0.dist-info/METADATA
make_better-0.5.0.dist-info/WHEEL
make_better-0.5.0.dist-info/entry_points.txt
make_better-0.5.0.dist-info/RECORD
