Metadata-Version: 2.1
Name: make_better
Version: 0.5.0
Summary: Easy lint and format you code
Home-page: https://github.com/Roktober/make_better
License: MIT
Keywords: autoformat,flake8,lint
Author: roktober
Requires-Python: >=3.8.1,<4.0.0
Classifier: Development Status :: 4 - Beta
Classifier: Environment :: Console
Classifier: Framework :: Flake8
Classifier: Intended Audience :: Developers
Classifier: License :: OSI Approved :: MIT License
Classifier: Operating System :: OS Independent
Classifier: Programming Language :: Python :: 3
Classifier: Programming Language :: Python :: 3.9
Classifier: Programming Language :: Python :: 3.10
Classifier: Programming Language :: Python :: 3.11
Classifier: Programming Language :: Python :: 3.12
Classifier: Topic :: Software Development :: Libraries :: Python Modules
Classifier: Topic :: Software Development :: Quality Assurance
Classifier: Typing :: Typed
Requires-Dist: bandit[toml] (>=1.7.5,<2.0.0)
Requires-Dist: black (>=23.1.0,<24.0.0)
Requires-Dist: flake8 (>=6.0.0,<7.0.0)
Requires-Dist: flake8-async (>=22.11.14,<23.0.0)
Requires-Dist: flake8-bugbear (>=23.2.13,<24.0.0)
Requires-Dist: flake8-comprehensions (>=3.10.1,<4.0.0)
Requires-Dist: flake8-datetimez (>=20.10.0,<21.0.0)
Requires-Dist: flake8-encodings (>=0.5.0.post1,<0.6.0)
Requires-Dist: flake8-import-conventions (>=0.1.0,<0.2.0)
Requires-Dist: flake8-print (>=5.0.0,<6.0.0)
Requires-Dist: flake8-return (>=1.2.0,<2.0.0)
Requires-Dist: flake8-use-pathlib (>=0.3.0,<0.4.0)
Requires-Dist: isort (>=5.12.0,<6.0.0)
Requires-Dist: tryceratops (>=2.3.2,<3.0.0)
Project-URL: Repository, https://github.com/Roktober/make_better
